examples/__init__.py
examples/collapse_fragility_fit.py
pyFragility/GLMClass.py
pyFragility/MLEClass.py
pyFragility/__init__.py
pyFragility-0.0.1.dist-info/LICENSE
pyFragility-0.0.1.dist-info/METADATA
pyFragility-0.0.1.dist-info/WHEEL
pyFragility-0.0.1.dist-info/top_level.txt
pyFragility-0.0.1.dist-info/RECORD
